npm_cli/__init__.py
npm_cli/__main__.py
npm_cli/api/__init__.py
npm_cli/api/client.py
npm_cli/api/exceptions.py
npm_cli/api/models.py
npm_cli/cli/__init__.py
npm_cli/cli/cert.py
npm_cli/cli/config.py
npm_cli/cli/proxy.py
npm_cli/config/__init__.py
npm_cli/config/settings.py
npm_cli/docker/__init__.py
npm_cli/docker/discovery.py
npm_cli/templates/__init__.py
npm_cli/templates/nginx.py
npm_cli-0.1.0.dist-info/WHEEL
npm_cli-0.1.0.dist-info/entry_points.txt
npm_cli-0.1.0.dist-info/METADATA
npm_cli-0.1.0.dist-info/RECORD
