Metadata-Version: 2.3
Name: npm-cli
Version: 0.1.0
Summary: Command-line tool for managing Nginx Proxy Manager via API
Keywords: nginx,proxy-manager,npm,cli,docker,ssl,certificate
Author: dan
Author-email: dan <dan@zumper.com>
License: MIT License
Classifier: Development Status :: 4 - Beta
Classifier: Intended Audience :: System Administrators
Classifier: License :: OSI Approved :: MIT License
Classifier: Programming Language :: Python :: 3
Classifier: Programming Language :: Python :: 3.11
Classifier: Programming Language :: Python :: 3.12
Classifier: Programming Language :: Python :: 3.13
Classifier: Topic :: System :: Systems Administration
Classifier: Topic :: Internet :: Proxy Servers
Classifier: Topic :: Security
Classifier: Environment :: Console
Requires-Dist: docker>=7.1.0
Requires-Dist: httpx>=0.28.1
Requires-Dist: pydantic>=2.12.5
Requires-Dist: pydantic-settings>=2.12.0
Requires-Dist: python-dotenv>=1.2.1
Requires-Dist: rich>=14.2.0
Requires-Dist: typer>=0.21.0
Requires-Python: >=3.11
Project-URL: Documentation, https://github.com/yourusername/npm-cli#readme
Project-URL: Homepage, https://github.com/yourusername/npm-cli
Project-URL: Issues, https://github.com/yourusername/npm-cli/issues
Project-URL: Repository, https://github.com/yourusername/npm-cli
